adcortex/__init__.py
adcortex/async_chat_client.py
adcortex/chat_client.py
adcortex/state.py
adcortex/types.py
adcortex-0.2.5.dist-info/METADATA
adcortex-0.2.5.dist-info/WHEEL
adcortex-0.2.5.dist-info/top_level.txt
adcortex-0.2.5.dist-info/RECORD
