Metadata-Version: 2.4
Name: adcortex
Version: 0.2.5
Summary: A Python SDK for Adcortex
Author-email: 3102Labs <3102labs@gmail.com>
Classifier: Programming Language :: Python :: 3
Classifier: License :: OSI Approved :: MIT License
Classifier: Operating System :: OS Independent
Requires-Python: >=3.8
Requires-Dist: requests>=2.31.0
Requires-Dist: httpx>=0.28.1
Requires-Dist: pycountry>=24.6.1
Requires-Dist: pydantic>=2.11.3
Requires-Dist: python-dotenv>=1.0.1
Requires-Dist: sphinx>=8.1.3
Requires-Dist: tenacity>=9.1.2
Provides-Extra: dev
Requires-Dist: pytest>=7.4.0; extra == "dev"
Requires-Dist: ruff>=0.1.1; extra == "dev"
Requires-Dist: mypy>=1.11.1; extra == "dev"
